LICENSE
README.md
setup.py
youtube_video_scraping/__init__.py
youtube_video_scraping.egg-info/PKG-INFO
youtube_video_scraping.egg-info/SOURCES.txt
youtube_video_scraping.egg-info/dependency_links.txt
youtube_video_scraping.egg-info/requires.txt
youtube_video_scraping.egg-info/top_level.txt