Metadata-Version: 2.1
Name: youtube-video-scraping
Version: 1.0.2
Summary: A python library to scrape video data from youtube automatically.
Home-page: https://youtube-api.datakund.com/en/latest/
Author: DataKund
Author-email: datakund@gmail.com
License: Apache License 2.0
Keywords: youtube python bot_studio video info scraper data web-scraping
Platform: UNKNOWN
License-File: LICENSE
